README.rst
log2jsconsole.py
setup.py
log2jsconsole.egg-info/PKG-INFO
log2jsconsole.egg-info/SOURCES.txt
log2jsconsole.egg-info/dependency_links.txt
log2jsconsole.egg-info/entry_points.txt
log2jsconsole.egg-info/requires.txt
log2jsconsole.egg-info/top_level.txt