Metadata-Version: 1.0
Name: log2jsconsole
Version: 0.4
Summary: Simple WSGI middleware that helps to log messages into JavaScript console object
Home-page: https://github.com/StyleShare/log2jsconsole
Author: Hong Minhee
Author-email: dahlia@stylesha.re
License: MIT License
Platform: UNKNOWN
